my_module.cp38-win_amd64.pyd
openimagepdemo-0.1.0.dist-info/METADATA
openimagepdemo-0.1.0.dist-info/WHEEL
openimagepdemo-0.1.0.dist-info/top_level.txt
openimagepdemo-0.1.0.dist-info/RECORD
