Metadata-Version: 2.1
Name: openimagepdemo
Version: 0.1.0
Summary: A sample Python module compiled with Cython
Author: Your Name
Author-email: your_email@example.com
Classifier: Programming Language :: Python
Classifier: Programming Language :: Cython
Classifier: License :: OSI Approved :: MIT License
Requires-Python: >=3.6
